turtleBeads.py
turtleBeads-1.1.3.dist-info/LICENSE.txt
turtleBeads-1.1.3.dist-info/METADATA
turtleBeads-1.1.3.dist-info/WHEEL
turtleBeads-1.1.3.dist-info/top_level.txt
turtleBeads-1.1.3.dist-info/RECORD
