Metadata-Version: 2.2
Name: turtleBeads
Version: 1.1.3
Summary: Turtle-based graphics library for drawing various shapes centered on the cursor. Also adds printed descriptions of what is drawn, including for built-in turtle functions.
Home-page: https://cs.wellesley.edu/~pmwh/turtleBeads/docs/turtleBeads
License: BSD 3-Clause License
Classifier: Programming Language :: Python :: 3 :: Only
Classifier: License :: OSI Approved :: BSD License
Classifier: Development Status :: 5 - Production/Stable
Classifier: Topic :: Multimedia :: Graphics
Classifier: Topic :: Education
Classifier: Intended Audience :: Education
Classifier: Intended Audience :: Developers
Classifier: Operating System :: OS Independent
Classifier: Natural Language :: English
License-File: LICENSE.txt
